pyp2p-0.8.2.dist-info/DESCRIPTION.rst
pyp2p-0.8.2.dist-info/metadata.json
pyp2p-0.8.2.dist-info/METADATA
pyp2p-0.8.2.dist-info/WHEEL
pyp2p-0.8.2.dist-info/top_level.txt
pyp2p-0.8.2.dist-info/RECORD
pyp2p/upnp.py
pyp2p/nat_pmp.py
pyp2p/ipgetter.py
pyp2p/sys_clock.py
pyp2p/__init__.py
pyp2p/net.py
pyp2p/ip_routes.py
pyp2p/hybrid_reply.py
pyp2p/sock.py
pyp2p/rendezvous_server.py
pyp2p/lib.py
pyp2p/rendezvous_client.py
pyp2p/unl.py
pyp2p/dht_msg.py
