Metadata-Version: 1.1
Name: pyp2p
Version: 0.8.2
Summary: Python P2P networking library
Home-page: http://github.com/Storj/pyp2p
Author: Storj
Author-email: matthew@storj.io
License: MIT
Keywords: NAT traversal,TCP hole punching,simultaneous open,UPnP,NATPMP,P2P,Peer-to-peer networking library,python
Platform: UNKNOWN
Classifier: Development Status :: 3 - Alpha
Classifier: Intended Audience :: Developers
Classifier: License :: OSI Approved :: MIT License
Classifier: Programming Language :: Python :: 2.7
Classifier: Programming Language :: Python :: 3
Classifier: Programming Language :: Python :: 3.2
Classifier: Programming Language :: Python :: 3.3
Classifier: Programming Language :: Python :: 3.4
